jsonpath_rw/__init__.py
jsonpath_rw/jsonpath.py
jsonpath_rw/lexer.py
jsonpath_rw/parser.py
jsonpath_rw/bin/__init__.py
jsonpath_rw/bin/jsonpath.py
dt_jsonpath_rw-1.4.0.dist-info/LICENSE
dt_jsonpath_rw-1.4.0.dist-info/METADATA
dt_jsonpath_rw-1.4.0.dist-info/WHEEL
dt_jsonpath_rw-1.4.0.dist-info/entry_points.txt
dt_jsonpath_rw-1.4.0.dist-info/top_level.txt
dt_jsonpath_rw-1.4.0.dist-info/RECORD
